{"name":"searchBySingleKeyword","id":"starter.wikipedia.WhenSearchingForTerms:searchBySingleKeyword","testCaseName":"starter.wikipedia.WhenSearchingForTerms","testSteps":[{"number":1,"description":"Navigate to the home page","duration":12527,"startTime":"2022-02-12T08:27:06.879084459Z[Etc/UTC]","screenshots":[{"screenshot":"0607aee65b5031d423dbcfc19647e36f5ddd0fae7feea6e8514af21767ae5dda.png","timeStamp":1644654439406}],"result":"SUCCESS","precondition":false,"level":0},{"number":2,"description":"Search by keyword \u0027Everest\u0027","duration":1586,"startTime":"2022-02-12T08:27:19.409782318Z[Etc/UTC]","screenshots":[{"screenshot":"a08163966f0a5cd6a7367c4c3e1b63e8a170806e33e0ddc263e3bf0eda703ae7.png","timeStamp":1644654440996}],"result":"SUCCESS","precondition":false,"level":0},{"number":3,"description":"The first heading should be \u0027Mount Everest\u0027","duration":207,"startTime":"2022-02-12T08:27:20.997129034Z[Etc/UTC]","screenshots":[{"screenshot":"a08163966f0a5cd6a7367c4c3e1b63e8a170806e33e0ddc263e3bf0eda703ae7.png","timeStamp":1644654441204}],"result":"SUCCESS","precondition":false,"level":0}],"userStory":{"id":"starter.wikipedia.WhenSearchingForTerms","storyName":"When searching for terms","displayName":"When searching for terms","storyClassName":"starter.wikipedia.WhenSearchingForTerms","path":"wikipedia","type":"story"},"featureTag":{"name":"Wikipedia/When searching for terms","type":"story","displayName":"Wikipedia/When searching for terms"},"title":"Search by single keyword","tags":[{"name":"Wikipedia/When searching for terms","type":"story","displayName":"When searching for terms"},{"name":"Wikipedia","type":"feature","displayName":"Wikipedia"}],"startTime":"2022-02-12T08:27:06.251734112Z[Etc/UTC]","duration":14966,"projectKey":"","sessionId":"2d5e63f88204dd9c0f0cceaec90270d7","driver":"chrome","isManualTestingUpToDate":false,"manual":false,"testSource":"JUnit5","order":0,"result":"SUCCESS"}